Workbook

Sheet Executive Summary
A1: MART INVENTORY & VALUATION DASHBOARD
A3: Automated POS Inventory Classification & Category Breakdown
A4: Total SKUs | B4: Total Stock Units | C4: Total Inventory Cost | D4: Total Retail Value | E4: Total Potential Profit | F4: Overall Margin %
A5: =COUNTA('Inventory (Sorted)'!A4:A730) | B5: =SUM('Inventory (Sorted)'!H4:H730) | C5: =SUM('Inventory (Sorted)'!I4:I730) | D5: =SUM('Inventory (Sorted)'!J4:J730) | E5: =D5-C5 | F5: =E5/D5
A8: CATEGORY WISE INVENTORY BREAKDOWN
A9: Category Group | B9: SKU Count | C9: Total Units | D9: Total Cost (PKR) | E9: Total Retail (PKR) | F9: Projected Margin (PKR) | G9: Margin %
A10: Store Assets & Equipment | B10: =COUNTIF('Inventory (Sorted)'!$C$4:$C$730, "Store Assets & Equipment") | C10: =SUMIF('Inventory (Sorted)'!$C$4:$C$730, "Store Assets & Equipment", 'Inventory (Sorted)'!$H$4:$H$730) | D10: =SUMIF('Inventory (Sorted)'!$C$4:$C$730, "Store Assets & Equipment", 'Inventory (Sorted)'!$I$4:$I$730) | E10: =SUMIF('Inventory (Sorted)'!$C$4:$C$730, "Store Assets & Equipment", 'Inventory (Sorted)'!$J$4:$J$730) | F10: =E10-D10 | G10: =IF(E10>0, F10/E10, 0)
A11: Beverages & Juices | B11: =COUNTIF('Inventory (Sorted)'!$C$4:$C$730, "Beverages & Juices") | C11: =SUMIF('Inventory (Sorted)'!$C$4:$C$730, "Beverages & Juices", 'Inventory (Sorted)'!$H$4:$H$730) | D11: =SUMIF('Inventory (Sorted)'!$C$4:$C$730, "Beverages & Juices", 'Inventory (Sorted)'!$I$4:$I$730) | E11: =SUMIF('Inventory (Sorted)'!$C$4:$C$730, "Beverages & Juices", 'Inventory (Sorted)'!$J$4:$J$730) | F11: =E11-D11 | G11: =IF(E11>0, F11/E11, 0)
A12: Cooking Oil & Ghee | B12: =COUNTIF('Inventory (Sorted)'!$C$4:$C$730, "Cooking Oil & Ghee") | C12: =SUMIF('Inventory (Sorted)'!$C$4:$C$730, "Cooking Oil & Ghee", 'Inventory (Sorted)'!$H$4:$H$730) | D12: =SUMIF('Inventory (Sorted)'!$C$4:$C$730, "Cooking Oil & Ghee", 'Inventory (Sorted)'!$I$4:$I$730) | E12: =SUMIF('Inventory (Sorted)'!$C$4:$C$730, "Cooking Oil & Ghee", 'Inventory (Sorted)'!$J$4:$J$730) | F12: =E12-D12 | G12: =IF(E12>0, F12/E12, 0)
A13: Rice & Staples | B13: =COUNTIF('Inventory (Sorted)'!$C$4:$C$730, "Rice & Staples") | C13: =SUMIF('Inventory (Sorted)'!$C$4:$C$730, "Rice & Staples", 'Inventory (Sorted)'!$H$4:$H$730) | D13: =SUMIF('Inventory (Sorted)'!$C$4:$C$730, "Rice & Staples", 'Inventory (Sorted)'!$I$4:$I$730) | E13: =SUMIF('Inventory (Sorted)'!$C$4:$C$730, "Rice & Staples", 'Inventory (Sorted)'!$J$4:$J$730) | F13: =E13-D13 | G13: =IF(E13>0, F13/E13, 0)
A14: Cigarettes & Tobacco | B14: =COUNTIF('Inventory (Sorted)'!$C$4:$C$730, "Cigarettes & Tobacco") | C14: =SUMIF('Inventory (Sorted)'!$C$4:$C$730, "Cigarettes & Tobacco", 'Inventory (Sorted)'!$H$4:$H$730) | D14: =SUMIF('Inventory (Sorted)'!$C$4:$C$730, "Cigarettes & Tobacco", 'Inventory (Sorted)'!$I$4:$I$730) | E14: =SUMIF('Inventory (Sorted)'!$C$4:$C$730, "Cigarettes & Tobacco", 'Inventory (Sorted)'!$J$4:$J$730) | F14: =E14-D14 | G14: =IF(E14>0, F14/E14, 0)
A15: Energy Drinks | B15: =COUNTIF('Inventory (Sorted)'!$C$4:$C$730, "Energy Drinks") | C15: =SUMIF('Inventory (Sorted)'!$C$4:$C$730, "Energy Drinks", 'Inventory (Sorted)'!$H$4:$H$730) | D15: =SUMIF('Inventory (Sorted)'!$C$4:$C$730, "Energy Drinks", 'Inventory (Sorted)'!$I$4:$I$730) | E15: =SUMIF('Inventory (Sorted)'!$C$4:$C$730, "Energy Drinks", 'Inventory (Sorted)'!$J$4:$J$730) | F15: =E15-D15 | G15: =IF(E15>0, F15/E15, 0)
A16: Baby Care | B16: =COUNTIF('Inventory (Sorted)'!$C$4:$C$730, "Baby Care") | C16: =SUMIF('Inventory (Sorted)'!$C$4:$C$730, "Baby Care", 'Inventory (Sorted)'!$H$4:$H$730) | D16: =SUMIF('Inventory (Sorted)'!$C$4:$C$730, "Baby Care", 'Inventory (Sorted)'!$I$4:$I$730) | E16: =SUMIF('Inventory (Sorted)'!$C$4:$C$730, "Baby Care", 'Inventory (Sorted)'!$J$4:$J$730) | F16: =E16-D16 | G16: =IF(E16>0, F16/E16, 0)
A17: Tea & Coffee | B17: =COUNTIF('Inventory (Sorted)'!$C$4:$C$730, "Tea & Coffee") | C17: =SUMIF('Inventory (Sorted)'!$C$4:$C$730, "Tea & Coffee", 'Inventory (Sorted)'!$H$4:$H$730) | D17: =SUMIF('Inventory (Sorted)'!$C$4:$C$730, "Tea & Coffee", 'Inventory (Sorted)'!$I$4:$I$730) | E17: =SUMIF('Inventory (Sorted)'!$C$4:$C$730, "Tea & Coffee", 'Inventory (Sorted)'!$J$4:$J$730) | F17: =E17-D17 | G17: =IF(E17>0, F17/E17, 0)
A18: Grains, Atta & Spices | B18: =COUNTIF('Inventory (Sorted)'!$C$4:$C$730, "Grains, Atta & Spices") | C18: =SUMIF('Inventory (Sorted)'!$C$4:$C$730, "Grains, Atta & Spices", 'Inventory (Sorted)'!$H$4:$H$730) | D18: =SUMIF('Inventory (Sorted)'!$C$4:$C$730, "Grains, Atta & Spices", 'Inventory (Sorted)'!$I$4:$I$730) | E18: =SUMIF('Inventory (Sorted)'!$C$4:$C$730, "Grains, Atta & Spices", 'Inventory (Sorted)'!$J$4:$J$730) | F18: =E18-D18 | G18: =IF(E18>0, F18/E18, 0)
A19: Biscuits & Bakery | B19: =COUNTIF('Inventory (Sorted)'!$C$4:$C$730, "Biscuits & Bakery") | C19: =SUMIF('Inventory (Sorted)'!$C$4:$C$730, "Biscuits & Bakery", 'Inventory (Sorted)'!$H$4:$H$730) | D19: =SUMIF('Inventory (Sorted)'!$C$4:$C$730, "Biscuits & Bakery", 'Inventory (Sorted)'!$I$4:$I$730) | E19: =SUMIF('Inventory (Sorted)'!$C$4:$C$730, "Biscuits & Bakery", 'Inventory (Sorted)'!$J$4:$J$730) | F19: =E19-D19 | G19: =IF(E19>0, F19/E19, 0)
A20: Item | B20: =COUNTIF('Inventory (Sorted)'!$C$4:$C$730, "Item") | C20: =SUMIF('Inventory (Sorted)'!$C$4:$C$730, "Item", 'Inventory (Sorted)'!$H$4:$H$730) | D20: =SUMIF('Inventory (Sorted)'!$C$4:$C$730, "Item", 'Inventory (Sorted)'!$I$4:$I$730) | E20: =SUMIF('Inventory (Sorted)'!$C$4:$C$730, "Item", 'Inventory (Sorted)'!$J$4:$J$730) | F20: =E20-D20 | G20: =IF(E20>0, F20/E20, 0)
A21: Personal Care & Hygiene | B21: =COUNTIF('Inventory (Sorted)'!$C$4:$C$730, "Personal Care & Hygiene") | C21: =SUMIF('Inventory (Sorted)'!$C$4:$C$730, "Personal Care & Hygiene", 'Inventory (Sorted)'!$H$4:$H$730) | D21: =SUMIF('Inventory (Sorted)'!$C$4:$C$730, "Personal Care & Hygiene", 'Inventory (Sorted)'!$I$4:$I$730) | E21: =SUMIF('Inventory (Sorted)'!$C$4:$C$730, "Personal Care & Hygiene", 'Inventory (Sorted)'!$J$4:$J$730) | F21: =E21-D21 | G21: =IF(E21>0, F21/E21, 0)
A22: Lentils & Pulses | B22: =COUNTIF('Inventory (Sorted)'!$C$4:$C$730, "Lentils & Pulses") | C22: =SUMIF('Inventory (Sorted)'!$C$4:$C$730, "Lentils & Pulses", 'Inventory (Sorted)'!$H$4:$H$730) | D22: =SUMIF('Inventory (Sorted)'!$C$4:$C$730, "Lentils & Pulses", 'Inventory (Sorted)'!$I$4:$I$730) | E22: =SUMIF('Inventory (Sorted)'!$C$4:$C$730, "Lentils & Pulses", 'Inventory (Sorted)'!$J$4:$J$730) | F22: =E22-D22 | G22: =IF(E22>0, F22/E22, 0)
A23: Cleaning & Household | B23: =COUNTIF('Inventory (Sorted)'!$C$4:$C$730, "Cleaning & Household") | C23: =SUMIF('Inventory (Sorted)'!$C$4:$C$730, "Cleaning & Household", 'Inventory (Sorted)'!$H$4:$H$730) | D23: =SUMIF('Inventory (Sorted)'!$C$4:$C$730, "Cleaning & Household", 'Inventory (Sorted)'!$I$4:$I$730) | E23: =SUMIF('Inventory (Sorted)'!$C$4:$C$730, "Cleaning & Household", 'Inventory (Sorted)'!$J$4:$J$730) | F23: =E23-D23 | G23: =IF(E23>0, F23/E23, 0)
A24: Cosmetics & Beauty | B24: =COUNTIF('Inventory (Sorted)'!$C$4:$C$730, "Cosmetics & Beauty") | C24: =SUMIF('Inventory (Sorted)'!$C$4:$C$730, "Cosmetics & Beauty", 'Inventory (Sorted)'!$H$4:$H$730) | D24: =SUMIF('Inventory (Sorted)'!$C$4:$C$730, "Cosmetics & Beauty", 'Inventory (Sorted)'!$I$4:$I$730) | E24: =SUMIF('Inventory (Sorted)'!$C$4:$C$730, "Cosmetics & Beauty", 'Inventory (Sorted)'!$J$4:$J$730) | F24: =E24-D24 | G24: =IF(E24>0, F24/E24, 0)
A25: Jam | B25: =COUNTIF('Inventory (Sorted)'!$C$4:$C$730, "Jam") | C25: =SUMIF('Inventory (Sorted)'!$C$4:$C$730, "Jam", 'Inventory (Sorted)'!$H$4:$H$730) | D25: =SUMIF('Inventory (Sorted)'!$C$4:$C$730, "Jam", 'Inventory (Sorted)'!$I$4:$I$730) | E25: =SUMIF('Inventory (Sorted)'!$C$4:$C$730, "Jam", 'Inventory (Sorted)'!$J$4:$J$730) | F25: =E25-D25 | G25: =IF(E25>0, F25/E25, 0)
A26: Tissues & Paper Goods | B26: =COUNTIF('Inventory (Sorted)'!$C$4:$C$730, "Tissues & Paper Goods") | C26: =SUMIF('Inventory (Sorted)'!$C$4:$C$730, "Tissues & Paper Goods", 'Inventory (Sorted)'!$H$4:$H$730) | D26: =SUMIF('Inventory (Sorted)'!$C$4:$C$730, "Tissues & Paper Goods", 'Inventory (Sorted)'!$I$4:$I$730) | E26: =SUMIF('Inventory (Sorted)'!$C$4:$C$730, "Tissues & Paper Goods", 'Inventory (Sorted)'!$J$4:$J$730) | F26: =E26-D26 | G26: =IF(E26>0, F26/E26, 0)
A27: Milk | B27: =COUNTIF('Inventory (Sorted)'!$C$4:$C$730, "Milk") | C27: =SUMIF('Inventory (Sorted)'!$C$4:$C$730, "Milk", 'Inventory (Sorted)'!$H$4:$H$730) | D27: =SUMIF('Inventory (Sorted)'!$C$4:$C$730, "Milk", 'Inventory (Sorted)'!$I$4:$I$730) | E27: =SUMIF('Inventory (Sorted)'!$C$4:$C$730, "Milk", 'Inventory (Sorted)'!$J$4:$J$730) | F27: =E27-D27 | G27: =IF(E27>0, F27/E27, 0)
A28: Tomato Paste | B28: =COUNTIF('Inventory (Sorted)'!$C$4:$C$730, "Tomato Paste") | C28: =SUMIF('Inventory (Sorted)'!$C$4:$C$730, "Tomato Paste", 'Inventory (Sorted)'!$H$4:$H$730) | D28: =SUMIF('Inventory (Sorted)'!$C$4:$C$730, "Tomato Paste", 'Inventory (Sorted)'!$I$4:$I$730) | E28: =SUMIF('Inventory (Sorted)'!$C$4:$C$730, "Tomato Paste", 'Inventory (Sorted)'!$J$4:$J$730) | F28: =E28-D28 | G28: =IF(E28>0, F28/E28, 0)
A29: Snacks & Nimko | B29: =COUNTIF('Inventory (Sorted)'!$C$4:$C$730, "Snacks & Nimko") | C29: =SUMIF('Inventory (Sorted)'!$C$4:$C$730, "Snacks & Nimko", 'Inventory (Sorted)'!$H$4:$H$730) | D29: =SUMIF('Inventory (Sorted)'!$C$4:$C$730, "Snacks & Nimko", 'Inventory (Sorted)'!$I$4:$I$730) | E29: =SUMIF('Inventory (Sorted)'!$C$4:$C$730, "Snacks & Nimko", 'Inventory (Sorted)'!$J$4:$J$730) | F29: =E29-D29 | G29: =IF(E29>0, F29/E29, 0)
A30: Laundry & Detergents | B30: =COUNTIF('Inventory (Sorted)'!$C$4:$C$730, "Laundry & Detergents") | C30: =SUMIF('Inventory (Sorted)'!$C$4:$C$730, "Laundry & Detergents", 'Inventory (Sorted)'!$H$4:$H$730) | D30: =SUMIF('Inventory (Sorted)'!$C$4:$C$730, "Laundry & Detergents", 'Inventory (Sorted)'!$I$4:$I$730) | E30: =SUMIF('Inventory (Sorted)'!$C$4:$C$730, "Laundry & Detergents", 'Inventory (Sorted)'!$J$4:$J$730) | F30: =E30-D30 | G30: =IF(E30>0, F30/E30, 0)
A31: Nutrition | B31: =COUNTIF('Inventory (Sorted)'!$C$4:$C$730, "Nutrition") | C31: =SUMIF('Inventory (Sorted)'!$C$4:$C$730, "Nutrition", 'Inventory (Sorted)'!$H$4:$H$730) | D31: =SUMIF('Inventory (Sorted)'!$C$4:$C$730, "Nutrition", 'Inventory (Sorted)'!$I$4:$I$730) | E31: =SUMIF('Inventory (Sorted)'!$C$4:$C$730, "Nutrition", 'Inventory (Sorted)'!$J$4:$J$730) | F31: =E31-D31 | G31: =IF(E31>0, F31/E31, 0)
A32: Test | B32: =COUNTIF('Inventory (Sorted)'!$C$4:$C$730, "Test") | C32: =SUMIF('Inventory (Sorted)'!$C$4:$C$730, "Test", 'Inventory (Sorted)'!$H$4:$H$730) | D32: =SUMIF('Inventory (Sorted)'!$C$4:$C$730, "Test", 'Inventory (Sorted)'!$I$4:$I$730) | E32: =SUMIF('Inventory (Sorted)'!$C$4:$C$730, "Test", 'Inventory (Sorted)'!$J$4:$J$730) | F32: =E32-D32 | G32: =IF(E32>0, F32/E32, 0)
A33: Perfumes & Body Sprays | B33: =COUNTIF('Inventory (Sorted)'!$C$4:$C$730, "Perfumes & Body Sprays") | C33: =SUMIF('Inventory (Sorted)'!$C$4:$C$730, "Perfumes & Body Sprays", 'Inventory (Sorted)'!$H$4:$H$730) | D33: =SUMIF('Inventory (Sorted)'!$C$4:$C$730, "Perfumes & Body Sprays", 'Inventory (Sorted)'!$I$4:$I$730) | E33: =SUMIF('Inventory (Sorted)'!$C$4:$C$730, "Perfumes & Body Sprays", 'Inventory (Sorted)'!$J$4:$J$730) | F33: =E33-D33 | G33: =IF(E33>0, F33/E33, 0)
A34: Ice Cream | B34: =COUNTIF('Inventory (Sorted)'!$C$4:$C$730, "Ice Cream") | C34: =SUMIF('Inventory (Sorted)'!$C$4:$C$730, "Ice Cream", 'Inventory (Sorted)'!$H$4:$H$730) | D34: =SUMIF('Inventory (Sorted)'!$C$4:$C$730, "Ice Cream", 'Inventory (Sorted)'!$I$4:$I$730) | E34: =SUMIF('Inventory (Sorted)'!$C$4:$C$730, "Ice Cream", 'Inventory (Sorted)'!$J$4:$J$730) | F34: =E34-D34 | G34: =IF(E34>0, F34/E34, 0)
A35: Noodles | B35: =COUNTIF('Inventory (Sorted)'!$C$4:$C$730, "Noodles") | C35: =SUMIF('Inventory (Sorted)'!$C$4:$C$730, "Noodles", 'Inventory (Sorted)'!$H$4:$H$730) | D35: =SUMIF('Inventory (Sorted)'!$C$4:$C$730, "Noodles", 'Inventory (Sorted)'!$I$4:$I$730) | E35: =SUMIF('Inventory (Sorted)'!$C$4:$C$730, "Noodles", 'Inventory (Sorted)'!$J$4:$J$730) | F35: =E35-D35 | G35: =IF(E35>0, F35/E35, 0)
A36: Dry Fruit | B36: =COUNTIF('Inventory (Sorted)'!$C$4:$C$730, "Dry Fruit") | C36: =SUMIF('Inventory (Sorted)'!$C$4:$C$730, "Dry Fruit", 'Inventory (Sorted)'!$H$4:$H$730) | D36: =SUMIF('Inventory (Sorted)'!$C$4:$C$730, "Dry Fruit", 'Inventory (Sorted)'!$I$4:$I$730) | E36: =SUMIF('Inventory (Sorted)'!$C$4:$C$730, "Dry Fruit", 'Inventory (Sorted)'!$J$4:$J$730) | F36: =E36-D36 | G36: =IF(E36>0, F36/E36, 0)
A37: Stain Remover | B37: =COUNTIF('Inventory (Sorted)'!$C$4:$C$730, "Stain Remover") | C37: =SUMIF('Inventory (Sorted)'!$C$4:$C$730, "Stain Remover", 'Inventory (Sorted)'!$H$4:$H$730) | D37: =SUMIF('Inventory (Sorted)'!$C$4:$C$730, "Stain Remover", 'Inventory (Sorted)'!$I$4:$I$730) | E37: =SUMIF('Inventory (Sorted)'!$C$4:$C$730, "Stain Remover", 'Inventory (Sorted)'!$J$4:$J$730) | F37: =E37-D37 | G37: =IF(E37>0, F37/E37, 0)
A38: Black Peper | B38: =COUNTIF('Inventory (Sorted)'!$C$4:$C$730, "Black Peper") | C38: =SUMIF('Inventory (Sorted)'!$C$4:$C$730, "Black Peper", 'Inventory (Sorted)'!$H$4:$H$730) | D38: =SUMIF('Inventory (Sorted)'!$C$4:$C$730, "Black Peper", 'Inventory (Sorted)'!$I$4:$I$730) | E38: =SUMIF('Inventory (Sorted)'!$C$4:$C$730, "Black Peper", 'Inventory (Sorted)'!$J$4:$J$730) | F38: =E38-D38 | G38: =IF(E38>0, F38/E38, 0)
A39: Cream | B39: =COUNTIF('Inventory (Sorted)'!$C$4:$C$730, "Cream") | C39: =SUMIF('Inventory (Sorted)'!$C$4:$C$730, "Cream", 'Inventory (Sorted)'!$H$4:$H$730) | D39: =SUMIF('Inventory (Sorted)'!$C$4:$C$730, "Cream", 'Inventory (Sorted)'!$I$4:$I$730) | E39: =SUMIF('Inventory (Sorted)'!$C$4:$C$730, "Cream", 'Inventory (Sorted)'!$J$4:$J$730) | F39: =E39-D39 | G39: =IF(E39>0, F39/E39, 0)
A40: Water | B40: =COUNTIF('Inventory (Sorted)'!$C$4:$C$730, "Water") | C40: =SUMIF('Inventory (Sorted)'!$C$4:$C$730, "Water", 'Inventory (Sorted)'!$H$4:$H$730) | D40: =SUMIF('Inventory (Sorted)'!$C$4:$C$730, "Water", 'Inventory (Sorted)'!$I$4:$I$730) | E40: =SUMIF('Inventory (Sorted)'!$C$4:$C$730, "Water", 'Inventory (Sorted)'!$J$4:$J$730) | F40: =E40-D40 | G40: =IF(E40>0, F40/E40, 0)
A41: Razor | B41: =COUNTIF('Inventory (Sorted)'!$C$4:$C$730, "Razor") | C41: =SUMIF('Inventory (Sorted)'!$C$4:$C$730, "Razor", 'Inventory (Sorted)'!$H$4:$H$730) | D41: =SUMIF('Inventory (Sorted)'!$C$4:$C$730, "Razor", 'Inventory (Sorted)'!$I$4:$I$730) | E41: =SUMIF('Inventory (Sorted)'!$C$4:$C$730, "Razor", 'Inventory (Sorted)'!$J$4:$J$730) | F41: =E41-D41 | G41: =IF(E41>0, F41/E41, 0)
A42: Chewing Gum & Mints | B42: =COUNTIF('Inventory (Sorted)'!$C$4:$C$730, "Chewing Gum & Mints") | C42: =SUMIF('Inventory (Sorted)'!$C$4:$C$730, "Chewing Gum & Mints", 'Inventory (Sorted)'!$H$4:$H$730) | D42: =SUMIF('Inventory (Sorted)'!$C$4:$C$730, "Chewing Gum & Mints", 'Inventory (Sorted)'!$I$4:$I$730) | E42: =SUMIF('Inventory (Sorted)'!$C$4:$C$730, "Chewing Gum & Mints", 'Inventory (Sorted)'!$J$4:$J$730) | F42: =E42-D42 | G42: =IF(E42>0, F42/E42, 0)
A43: Macroni | B43: =COUNTIF('Inventory (Sorted)'!$C$4:$C$730, "Macroni") | C43: =SUMIF('Inventory (Sorted)'!$C$4:$C$730, "Macroni", 'Inventory (Sorted)'!$H$4:$H$730) | D43: =SUMIF('Inventory (Sorted)'!$C$4:$C$730, "Macroni", 'Inventory (Sorted)'!$I$4:$I$730) | E43: =SUMIF('Inventory (Sorted)'!$C$4:$C$730, "Macroni", 'Inventory (Sorted)'!$J$4:$J$730) | F43: =E43-D43 | G43: =IF(E43>0, F43/E43, 0)
A44: Mosquito Killer | B44: =COUNTIF('Inventory (Sorted)'!$C$4:$C$730, "Mosquito Killer") | C44: =SUMIF('Inventory (Sorted)'!$C$4:$C$730, "Mosquito Killer", 'Inventory (Sorted)'!$H$4:$H$730) | D44: =SUMIF('Inventory (Sorted)'!$C$4:$C$730, "Mosquito Killer", 'Inventory (Sorted)'!$I$4:$I$730) | E44: =SUMIF('Inventory (Sorted)'!$C$4:$C$730, "Mosquito Killer", 'Inventory (Sorted)'!$J$4:$J$730) | F44: =E44-D44 | G44: =IF(E44>0, F44/E44, 0)
A45: Hair Care & Colour | B45: =COUNTIF('Inventory (Sorted)'!$C$4:$C$730, "Hair Care & Colour") | C45: =SUMIF('Inventory (Sorted)'!$C$4:$C$730, "Hair Care & Colour", 'Inventory (Sorted)'!$H$4:$H$730) | D45: =SUMIF('Inventory (Sorted)'!$C$4:$C$730, "Hair Care & Colour", 'Inventory (Sorted)'!$I$4:$I$730) | E45: =SUMIF('Inventory (Sorted)'!$C$4:$C$730, "Hair Care & Colour", 'Inventory (Sorted)'!$J$4:$J$730) | F45: =E45-D45 | G45: =IF(E45>0, F45/E45, 0)
A46: Cheese | B46: =COUNTIF('Inventory (Sorted)'!$C$4:$C$730, "Cheese") | C46: =SUMIF('Inventory (Sorted)'!$C$4:$C$730, "Cheese", 'Inventory (Sorted)'!$H$4:$H$730) | D46: =SUMIF('Inventory (Sorted)'!$C$4:$C$730, "Cheese", 'Inventory (Sorted)'!$I$4:$I$730) | E46: =SUMIF('Inventory (Sorted)'!$C$4:$C$730, "Cheese", 'Inventory (Sorted)'!$J$4:$J$730) | F46: =E46-D46 | G46: =IF(E46>0, F46/E46, 0)
A47: Pickled | B47: =COUNTIF('Inventory (Sorted)'!$C$4:$C$730, "Pickled") | C47: =SUMIF('Inventory (Sorted)'!$C$4:$C$730, "Pickled", 'Inventory (Sorted)'!$H$4:$H$730) | D47: =SUMIF('Inventory (Sorted)'!$C$4:$C$730, "Pickled", 'Inventory (Sorted)'!$I$4:$I$730) | E47: =SUMIF('Inventory (Sorted)'!$C$4:$C$730, "Pickled", 'Inventory (Sorted)'!$J$4:$J$730) | F47: =E47-D47 | G47: =IF(E47>0, F47/E47, 0)
A48: Qroot | B48: =COUNTIF('Inventory (Sorted)'!$C$4:$C$730, "Qroot") | C48: =SUMIF('Inventory (Sorted)'!$C$4:$C$730, "Qroot", 'Inventory (Sorted)'!$H$4:$H$730) | D48: =SUMIF('Inventory (Sorted)'!$C$4:$C$730, "Qroot", 'Inventory (Sorted)'!$I$4:$I$730) | E48: =SUMIF('Inventory (Sorted)'!$C$4:$C$730, "Qroot", 'Inventory (Sorted)'!$J$4:$J$730) | F48: =E48-D48 | G48: =IF(E48>0, F48/E48, 0)
A49: Food | B49: =COUNTIF('Inventory (Sorted)'!$C$4:$C$730, "Food") | C49: =SUMIF('Inventory (Sorted)'!$C$4:$C$730, "Food", 'Inventory (Sorted)'!$H$4:$H$730) | D49: =SUMIF('Inventory (Sorted)'!$C$4:$C$730, "Food", 'Inventory (Sorted)'!$I$4:$I$730) | E49: =SUMIF('Inventory (Sorted)'!$C$4:$C$730, "Food", 'Inventory (Sorted)'!$J$4:$J$730) | F49: =E49-D49 | G49: =IF(E49>0, F49/E49, 0)
A50: Oral Care | B50: =COUNTIF('Inventory (Sorted)'!$C$4:$C$730, "Oral Care") | C50: =SUMIF('Inventory (Sorted)'!$C$4:$C$730, "Oral Care", 'Inventory (Sorted)'!$H$4:$H$730) | D50: =SUMIF('Inventory (Sorted)'!$C$4:$C$730, "Oral Care", 'Inventory (Sorted)'!$I$4:$I$730) | E50: =SUMIF('Inventory (Sorted)'!$C$4:$C$730, "Oral Care", 'Inventory (Sorted)'!$J$4:$J$730) | F50: =E50-D50 | G50: =IF(E50>0, F50/E50, 0)
A51: Drain Opener | B51: =COUNTIF('Inventory (Sorted)'!$C$4:$C$730, "Drain Opener") | C51: =SUMIF('Inventory (Sorted)'!$C$4:$C$730, "Drain Opener", 'Inventory (Sorted)'!$H$4:$H$730) | D51: =SUMIF('Inventory (Sorted)'!$C$4:$C$730, "Drain Opener", 'Inventory (Sorted)'!$I$4:$I$730) | E51: =SUMIF('Inventory (Sorted)'!$C$4:$C$730, "Drain Opener", 'Inventory (Sorted)'!$J$4:$J$730) | F51: =E51-D51 | G51: =IF(E51>0, F51/E51, 0)
A52: White Oats | B52: =COUNTIF('Inventory (Sorted)'!$C$4:$C$730, "White Oats") | C52: =SUMIF('Inventory (Sorted)'!$C$4:$C$730, "White Oats", 'Inventory (Sorted)'!$H$4:$H$730) | D52: =SUMIF('Inventory (Sorted)'!$C$4:$C$730, "White Oats", 'Inventory (Sorted)'!$I$4:$I$730) | E52: =SUMIF('Inventory (Sorted)'!$C$4:$C$730, "White Oats", 'Inventory (Sorted)'!$J$4:$J$730) | F52: =E52-D52 | G52: =IF(E52>0, F52/E52, 0)
A53: Spray | B53: =COUNTIF('Inventory (Sorted)'!$C$4:$C$730, "Spray") | C53: =SUMIF('Inventory (Sorted)'!$C$4:$C$730, "Spray", 'Inventory (Sorted)'!$H$4:$H$730) | D53: =SUMIF('Inventory (Sorted)'!$C$4:$C$730, "Spray", 'Inventory (Sorted)'!$I$4:$I$730) | E53: =SUMIF('Inventory (Sorted)'!$C$4:$C$730, "Spray", 'Inventory (Sorted)'!$J$4:$J$730) | F53: =E53-D53 | G53: =IF(E53>0, F53/E53, 0)
A54: Tolit Jel | B54: =COUNTIF('Inventory (Sorted)'!$C$4:$C$730, "Tolit Jel") | C54: =SUMIF('Inventory (Sorted)'!$C$4:$C$730, "Tolit Jel", 'Inventory (Sorted)'!$H$4:$H$730) | D54: =SUMIF('Inventory (Sorted)'!$C$4:$C$730, "Tolit Jel", 'Inventory (Sorted)'!$I$4:$I$730) | E54: =SUMIF('Inventory (Sorted)'!$C$4:$C$730, "Tolit Jel", 'Inventory (Sorted)'!$J$4:$J$730) | F54: =E54-D54 | G54: =IF(E54>0, F54/E54, 0)
A55: Marker | B55: =COUNTIF('Inventory (Sorted)'!$C$4:$C$730, "Marker") | C55: =SUMIF('Inventory (Sorted)'!$C$4:$C$730, "Marker", 'Inventory (Sorted)'!$H$4:$H$730) | D55: =SUMIF('Inventory (Sorted)'!$C$4:$C$730, "Marker", 'Inventory (Sorted)'!$I$4:$I$730) | E55: =SUMIF('Inventory (Sorted)'!$C$4:$C$730, "Marker", 'Inventory (Sorted)'!$J$4:$J$730) | F55: =E55-D55 | G55: =IF(E55>0, F55/E55, 0)
A56: Dates | B56: =COUNTIF('Inventory (Sorted)'!$C$4:$C$730, "Dates") | C56: =SUMIF('Inventory (Sorted)'!$C$4:$C$730, "Dates", 'Inventory (Sorted)'!$H$4:$H$730) | D56: =SUMIF('Inventory (Sorted)'!$C$4:$C$730, "Dates", 'Inventory (Sorted)'!$I$4:$I$730) | E56: =SUMIF('Inventory (Sorted)'!$C$4:$C$730, "Dates", 'Inventory (Sorted)'!$J$4:$J$730) | F56: =E56-D56 | G56: =IF(E56>0, F56/E56, 0)
A57: Glass | B57: =COUNTIF('Inventory (Sorted)'!$C$4:$C$730, "Glass") | C57: =SUMIF('Inventory (Sorted)'!$C$4:$C$730, "Glass", 'Inventory (Sorted)'!$H$4:$H$730) | D57: =SUMIF('Inventory (Sorted)'!$C$4:$C$730, "Glass", 'Inventory (Sorted)'!$I$4:$I$730) | E57: =SUMIF('Inventory (Sorted)'!$C$4:$C$730, "Glass", 'Inventory (Sorted)'!$J$4:$J$730) | F57: =E57-D57 | G57: =IF(E57>0, F57/E57, 0)
A58: Liquid | B58: =COUNTIF('Inventory (Sorted)'!$C$4:$C$730, "Liquid") | C58: =SUMIF('Inventory (Sorted)'!$C$4:$C$730, "Liquid", 'Inventory (Sorted)'!$H$4:$H$730) | D58: =SUMIF('Inventory (Sorted)'!$C$4:$C$730, "Liquid", 'Inventory (Sorted)'!$I$4:$I$730) | E58: =SUMIF('Inventory (Sorted)'!$C$4:$C$730, "Liquid", 'Inventory (Sorted)'!$J$4:$J$730) | F58: =E58-D58 | G58: =IF(E58>0, F58/E58, 0)
A59: Honey | B59: =COUNTIF('Inventory (Sorted)'!$C$4:$C$730, "Honey") | C59: =SUMIF('Inventory (Sorted)'!$C$4:$C$730, "Honey", 'Inventory (Sorted)'!$H$4:$H$730) | D59: =SUMIF('Inventory (Sorted)'!$C$4:$C$730, "Honey", 'Inventory (Sorted)'!$I$4:$I$730) | E59: =SUMIF('Inventory (Sorted)'!$C$4:$C$730, "Honey", 'Inventory (Sorted)'!$J$4:$J$730) | F59: =E59-D59 | G59: =IF(E59>0, F59/E59, 0)
A60: Spaghetti | B60: =COUNTIF('Inventory (Sorted)'!$C$4:$C$730, "Spaghetti") | C60: =SUMIF('Inventory (Sorted)'!$C$4:$C$730, "Spaghetti", 'Inventory (Sorted)'!$H$4:$H$730) | D60: =SUMIF('Inventory (Sorted)'!$C$4:$C$730, "Spaghetti", 'Inventory (Sorted)'!$I$4:$I$730) | E60: =SUMIF('Inventory (Sorted)'!$C$4:$C$730, "Spaghetti", 'Inventory (Sorted)'!$J$4:$J$730) | F60: =E60-D60 | G60: =IF(E60>0, F60/E60, 0)
A61: Confectionery & Sweets | B61: =COUNTIF('Inventory (Sorted)'!$C$4:$C$730, "Confectionery & Sweets") | C61: =SUMIF('Inventory (Sorted)'!$C$4:$C$730, "Confectionery & Sweets", 'Inventory (Sorted)'!$H$4:$H$730) | D61: =SUMIF('Inventory (Sorted)'!$C$4:$C$730, "Confectionery & Sweets", 'Inventory (Sorted)'!$I$4:$I$730) | E61: =SUMIF('Inventory (Sorted)'!$C$4:$C$730, "Confectionery & Sweets", 'Inventory (Sorted)'!$J$4:$J$730) | F61: =E61-D61 | G61: =IF(E61>0, F61/E61, 0)
A62: Masala | B62: =COUNTIF('Inventory (Sorted)'!$C$4:$C$730, "Masala") | C62: =SUMIF('Inventory (Sorted)'!$C$4:$C$730, "Masala", 'Inventory (Sorted)'!$H$4:$H$730) | D62: =SUMIF('Inventory (Sorted)'!$C$4:$C$730, "Masala", 'Inventory (Sorted)'!$I$4:$I$730) | E62: =SUMIF('Inventory (Sorted)'!$C$4:$C$730, "Masala", 'Inventory (Sorted)'!$J$4:$J$730) | F62: =E62-D62 | G62: =IF(E62>0, F62/E62, 0)
A63: Chocolates & Candy | B63: =COUNTIF('Inventory (Sorted)'!$C$4:$C$730, "Chocolates & Candy") | C63: =SUMIF('Inventory (Sorted)'!$C$4:$C$730, "Chocolates & Candy", 'Inventory (Sorted)'!$H$4:$H$730) | D63: =SUMIF('Inventory (Sorted)'!$C$4:$C$730, "Chocolates & Candy", 'Inventory (Sorted)'!$I$4:$I$730) | E63: =SUMIF('Inventory (Sorted)'!$C$4:$C$730, "Chocolates & Candy", 'Inventory (Sorted)'!$J$4:$J$730) | F63: =E63-D63 | G63: =IF(E63>0, F63/E63, 0)
A64: Milk Powder | B64: =COUNTIF('Inventory (Sorted)'!$C$4:$C$730, "Milk Powder") | C64: =SUMIF('Inventory (Sorted)'!$C$4:$C$730, "Milk Powder", 'Inventory (Sorted)'!$H$4:$H$730) | D64: =SUMIF('Inventory (Sorted)'!$C$4:$C$730, "Milk Powder", 'Inventory (Sorted)'!$I$4:$I$730) | E64: =SUMIF('Inventory (Sorted)'!$C$4:$C$730, "Milk Powder", 'Inventory (Sorted)'!$J$4:$J$730) | F64: =E64-D64 | G64: =IF(E64>0, F64/E64, 0)
A65: Sponge | B65: =COUNTIF('Inventory (Sorted)'!$C$4:$C$730, "Sponge") | C65: =SUMIF('Inventory (Sorted)'!$C$4:$C$730, "Sponge", 'Inventory (Sorted)'!$H$4:$H$730) | D65: =SUMIF('Inventory (Sorted)'!$C$4:$C$730, "Sponge", 'Inventory (Sorted)'!$I$4:$I$730) | E65: =SUMIF('Inventory (Sorted)'!$C$4:$C$730, "Sponge", 'Inventory (Sorted)'!$J$4:$J$730) | F65: =E65-D65 | G65: =IF(E65>0, F65/E65, 0)
A66: Corn | B66: =COUNTIF('Inventory (Sorted)'!$C$4:$C$730, "Corn") | C66: =SUMIF('Inventory (Sorted)'!$C$4:$C$730, "Corn", 'Inventory (Sorted)'!$H$4:$H$730) | D66: =SUMIF('Inventory (Sorted)'!$C$4:$C$730, "Corn", 'Inventory (Sorted)'!$I$4:$I$730) | E66: =SUMIF('Inventory (Sorted)'!$C$4:$C$730, "Corn", 'Inventory (Sorted)'!$J$4:$J$730) | F66: =E66-D66 | G66: =IF(E66>0, F66/E66, 0)
A67: Air Freshner | B67: =COUNTIF('Inventory (Sorted)'!$C$4:$C$730, "Air Freshner") | C67: =SUMIF('Inventory (Sorted)'!$C$4:$C$730, "Air Freshner", 'Inventory (Sorted)'!$H$4:$H$730) | D67: =SUMIF('Inventory (Sorted)'!$C$4:$C$730, "Air Freshner", 'Inventory (Sorted)'!$I$4:$I$730) | E67: =SUMIF('Inventory (Sorted)'!$C$4:$C$730, "Air Freshner", 'Inventory (Sorted)'!$J$4:$J$730) | F67: =E67-D67 | G67: =IF(E67>0, F67/E67, 0)
A68: Hand Wash | B68: =COUNTIF('Inventory (Sorted)'!$C$4:$C$730, "Hand Wash") | C68: =SUMIF('Inventory (Sorted)'!$C$4:$C$730, "Hand Wash", 'Inventory (Sorted)'!$H$4:$H$730) | D68: =SUMIF('Inventory (Sorted)'!$C$4:$C$730, "Hand Wash", 'Inventory (Sorted)'!$I$4:$I$730) | E68: =SUMIF('Inventory (Sorted)'!$C$4:$C$730, "Hand Wash", 'Inventory (Sorted)'!$J$4:$J$730) | F68: =E68-D68 | G68: =IF(E68>0, F68/E68, 0)
A69: Egg | B69: =COUNTIF('Inventory (Sorted)'!$C$4:$C$730, "Egg") | C69: =SUMIF('Inventory (Sorted)'!$C$4:$C$730, "Egg", 'Inventory (Sorted)'!$H$4:$H$730) | D69: =SUMIF('Inventory (Sorted)'!$C$4:$C$730, "Egg", 'Inventory (Sorted)'!$I$4:$I$730) | E69: =SUMIF('Inventory (Sorted)'!$C$4:$C$730, "Egg", 'Inventory (Sorted)'!$J$4:$J$730) | F69: =E69-D69 | G69: =IF(E69>0, F69/E69, 0)
A70: Chana | B70: =COUNTIF('Inventory (Sorted)'!$C$4:$C$730, "Chana") | C70: =SUMIF('Inventory (Sorted)'!$C$4:$C$730, "Chana", 'Inventory (Sorted)'!$H$4:$H$730) | D70: =SUMIF('Inventory (Sorted)'!$C$4:$C$730, "Chana", 'Inventory (Sorted)'!$I$4:$I$730) | E70: =SUMIF('Inventory (Sorted)'!$C$4:$C$730, "Chana", 'Inventory (Sorted)'!$J$4:$J$730) | F70: =E70-D70 | G70: =IF(E70>0, F70/E70, 0)
A71: Peanut | B71: =COUNTIF('Inventory (Sorted)'!$C$4:$C$730, "Peanut") | C71: =SUMIF('Inventory (Sorted)'!$C$4:$C$730, "Peanut", 'Inventory (Sorted)'!$H$4:$H$730) | D71: =SUMIF('Inventory (Sorted)'!$C$4:$C$730, "Peanut", 'Inventory (Sorted)'!$I$4:$I$730) | E71: =SUMIF('Inventory (Sorted)'!$C$4:$C$730, "Peanut", 'Inventory (Sorted)'!$J$4:$J$730) | F71: =E71-D71 | G71: =IF(E71>0, F71/E71, 0)
A72: Lock | B72: =COUNTIF('Inventory (Sorted)'!$C$4:$C$730, "Lock") | C72: =SUMIF('Inventory (Sorted)'!$C$4:$C$730, "Lock", 'Inventory (Sorted)'!$H$4:$H$730) | D72: =SUMIF('Inventory (Sorted)'!$C$4:$C$730, "Lock", 'Inventory (Sorted)'!$I$4:$I$730) | E72: =SUMIF('Inventory (Sorted)'!$C$4:$C$730, "Lock", 'Inventory (Sorted)'!$J$4:$J$730) | F72: =E72-D72 | G72: =IF(E72>0, F72/E72, 0)
A73: Tuna Fish | B73: =COUNTIF('Inventory (Sorted)'!$C$4:$C$730, "Tuna Fish") | C73: =SUMIF('Inventory (Sorted)'!$C$4:$C$730, "Tuna Fish", 'Inventory (Sorted)'!$H$4:$H$730) | D73: =SUMIF('Inventory (Sorted)'!$C$4:$C$730, "Tuna Fish", 'Inventory (Sorted)'!$I$4:$I$730) | E73: =SUMIF('Inventory (Sorted)'!$C$4:$C$730, "Tuna Fish", 'Inventory (Sorted)'!$J$4:$J$730) | F73: =E73-D73 | G73: =IF(E73>0, F73/E73, 0)
A74: Neel | B74: =COUNTIF('Inventory (Sorted)'!$C$4:$C$730, "Neel") | C74: =SUMIF('Inventory (Sorted)'!$C$4:$C$730, "Neel", 'Inventory (Sorted)'!$H$4:$H$730) | D74: =SUMIF('Inventory (Sorted)'!$C$4:$C$730, "Neel", 'Inventory (Sorted)'!$I$4:$I$730) | E74: =SUMIF('Inventory (Sorted)'!$C$4:$C$730, "Neel", 'Inventory (Sorted)'!$J$4:$J$730) | F74: =E74-D74 | G74: =IF(E74>0, F74/E74, 0)
A75: Safety | B75: =COUNTIF('Inventory (Sorted)'!$C$4:$C$730, "Safety") | C75: =SUMIF('Inventory (Sorted)'!$C$4:$C$730, "Safety", 'Inventory (Sorted)'!$H$4:$H$730) | D75: =SUMIF('Inventory (Sorted)'!$C$4:$C$730, "Safety", 'Inventory (Sorted)'!$I$4:$I$730) | E75: =SUMIF('Inventory (Sorted)'!$C$4:$C$730, "Safety", 'Inventory (Sorted)'!$J$4:$J$730) | F75: =E75-D75 | G75: =IF(E75>0, F75/E75, 0)
A76: Vermicelli | B76: =COUNTIF('Inventory (Sorted)'!$C$4:$C$730, "Vermicelli") | C76: =SUMIF('Inventory (Sorted)'!$C$4:$C$730, "Vermicelli", 'Inventory (Sorted)'!$H$4:$H$730) | D76: =SUMIF('Inventory (Sorted)'!$C$4:$C$730, "Vermicelli", 'Inventory (Sorted)'!$I$4:$I$730) | E76: =SUMIF('Inventory (Sorted)'!$C$4:$C$730, "Vermicelli", 'Inventory (Sorted)'!$J$4:$J$730) | F76: =E76-D76 | G76: =IF(E76>0, F76/E76, 0)
A77: Medicine | B77: =COUNTIF('Inventory (Sorted)'!$C$4:$C$730, "Medicine") | C77: =SUMIF('Inventory (Sorted)'!$C$4:$C$730, "Medicine", 'Inventory (Sorted)'!$H$4:$H$730) | D77: =SUMIF('Inventory (Sorted)'!$C$4:$C$730, "Medicine", 'Inventory (Sorted)'!$I$4:$I$730) | E77: =SUMIF('Inventory (Sorted)'!$C$4:$C$730, "Medicine", 'Inventory (Sorted)'!$J$4:$J$730) | F77: =E77-D77 | G77: =IF(E77>0, F77/E77, 0)
A78: Bin Plastic | B78: =COUNTIF('Inventory (Sorted)'!$C$4:$C$730, "Bin Plastic") | C78: =SUMIF('Inventory (Sorted)'!$C$4:$C$730, "Bin Plastic", 'Inventory (Sorted)'!$H$4:$H$730) | D78: =SUMIF('Inventory (Sorted)'!$C$4:$C$730, "Bin Plastic", 'Inventory (Sorted)'!$I$4:$I$730) | E78: =SUMIF('Inventory (Sorted)'!$C$4:$C$730, "Bin Plastic", 'Inventory (Sorted)'!$J$4:$J$730) | F78: =E78-D78 | G78: =IF(E78>0, F78/E78, 0)
A79: Cocktail | B79: =COUNTIF('Inventory (Sorted)'!$C$4:$C$730, "Cocktail") | C79: =SUMIF('Inventory (Sorted)'!$C$4:$C$730, "Cocktail", 'Inventory (Sorted)'!$H$4:$H$730) | D79: =SUMIF('Inventory (Sorted)'!$C$4:$C$730, "Cocktail", 'Inventory (Sorted)'!$I$4:$I$730) | E79: =SUMIF('Inventory (Sorted)'!$C$4:$C$730, "Cocktail", 'Inventory (Sorted)'!$J$4:$J$730) | F79: =E79-D79 | G79: =IF(E79>0, F79/E79, 0)
A80: Chicken Cube | B80: =COUNTIF('Inventory (Sorted)'!$C$4:$C$730, "Chicken Cube") | C80: =SUMIF('Inventory (Sorted)'!$C$4:$C$730, "Chicken Cube", 'Inventory (Sorted)'!$H$4:$H$730) | D80: =SUMIF('Inventory (Sorted)'!$C$4:$C$730, "Chicken Cube", 'Inventory (Sorted)'!$I$4:$I$730) | E80: =SUMIF('Inventory (Sorted)'!$C$4:$C$730, "Chicken Cube", 'Inventory (Sorted)'!$J$4:$J$730) | F80: =E80-D80 | G80: =IF(E80>0, F80/E80, 0)
A81: Lighter | B81: =COUNTIF('Inventory (Sorted)'!$C$4:$C$730, "Lighter") | C81: =SUMIF('Inventory (Sorted)'!$C$4:$C$730, "Lighter", 'Inventory (Sorted)'!$H$4:$H$730) | D81: =SUMIF('Inventory (Sorted)'!$C$4:$C$730, "Lighter", 'Inventory (Sorted)'!$I$4:$I$730) | E81: =SUMIF('Inventory (Sorted)'!$C$4:$C$730, "Lighter", 'Inventory (Sorted)'!$J$4:$J$730) | F81: =E81-D81 | G81: =IF(E81>0, F81/E81, 0)
A82: Matchbox | B82: =COUNTIF('Inventory (Sorted)'!$C$4:$C$730, "Matchbox") | C82: =SUMIF('Inventory (Sorted)'!$C$4:$C$730, "Matchbox", 'Inventory (Sorted)'!$H$4:$H$730) | D82: =SUMIF('Inventory (Sorted)'!$C$4:$C$730, "Matchbox", 'Inventory (Sorted)'!$I$4:$I$730) | E82: =SUMIF('Inventory (Sorted)'!$C$4:$C$730, "Matchbox", 'Inventory (Sorted)'!$J$4:$J$730) | F82: =E82-D82 | G82: =IF(E82>0, F82/E82, 0)
A83: Biryani | B83: =COUNTIF('Inventory (Sorted)'!$C$4:$C$730, "Biryani") | C83: =SUMIF('Inventory (Sorted)'!$C$4:$C$730, "Biryani", 'Inventory (Sorted)'!$H$4:$H$730) | D83: =SUMIF('Inventory (Sorted)'!$C$4:$C$730, "Biryani", 'Inventory (Sorted)'!$I$4:$I$730) | E83: =SUMIF('Inventory (Sorted)'!$C$4:$C$730, "Biryani", 'Inventory (Sorted)'!$J$4:$J$730) | F83: =E83-D83 | G83: =IF(E83>0, F83/E83, 0)
A84: Mask | B84: =COUNTIF('Inventory (Sorted)'!$C$4:$C$730, "Mask") | C84: =SUMIF('Inventory (Sorted)'!$C$4:$C$730, "Mask", 'Inventory (Sorted)'!$H$4:$H$730) | D84: =SUMIF('Inventory (Sorted)'!$C$4:$C$730, "Mask", 'Inventory (Sorted)'!$I$4:$I$730) | E84: =SUMIF('Inventory (Sorted)'!$C$4:$C$730, "Mask", 'Inventory (Sorted)'!$J$4:$J$730) | F84: =E84-D84 | G84: =IF(E84>0, F84/E84, 0)
A85: Mirror | B85: =COUNTIF('Inventory (Sorted)'!$C$4:$C$730, "Mirror") | C85: =SUMIF('Inventory (Sorted)'!$C$4:$C$730, "Mirror", 'Inventory (Sorted)'!$H$4:$H$730) | D85: =SUMIF('Inventory (Sorted)'!$C$4:$C$730, "Mirror", 'Inventory (Sorted)'!$I$4:$I$730) | E85: =SUMIF('Inventory (Sorted)'!$C$4:$C$730, "Mirror", 'Inventory (Sorted)'!$J$4:$J$730) | F85: =E85-D85 | G85: =IF(E85>0, F85/E85, 0)
A86: Sharbat | B86: =COUNTIF('Inventory (Sorted)'!$C$4:$C$730, "Sharbat") | C86: =SUMIF('Inventory (Sorted)'!$C$4:$C$730, "Sharbat", 'Inventory (Sorted)'!$H$4:$H$730) | D86: =SUMIF('Inventory (Sorted)'!$C$4:$C$730, "Sharbat", 'Inventory (Sorted)'!$I$4:$I$730) | E86: =SUMIF('Inventory (Sorted)'!$C$4:$C$730, "Sharbat", 'Inventory (Sorted)'!$J$4:$J$730) | F86: =E86-D86 | G86: =IF(E86>0, F86/E86, 0)
A87: Samad Bond | B87: =COUNTIF('Inventory (Sorted)'!$C$4:$C$730, "Samad Bond") | C87: =SUMIF('Inventory (Sorted)'!$C$4:$C$730, "Samad Bond", 'Inventory (Sorted)'!$H$4:$H$730) | D87: =SUMIF('Inventory (Sorted)'!$C$4:$C$730, "Samad Bond", 'Inventory (Sorted)'!$I$4:$I$730) | E87: =SUMIF('Inventory (Sorted)'!$C$4:$C$730, "Samad Bond", 'Inventory (Sorted)'!$J$4:$J$730) | F87: =E87-D87 | G87: =IF(E87>0, F87/E87, 0)
A88: Sopdyee | B88: =COUNTIF('Inventory (Sorted)'!$C$4:$C$730, "Sopdyee") | C88: =SUMIF('Inventory (Sorted)'!$C$4:$C$730, "Sopdyee", 'Inventory (Sorted)'!$H$4:$H$730) | D88: =SUMIF('Inventory (Sorted)'!$C$4:$C$730, "Sopdyee", 'Inventory (Sorted)'!$I$4:$I$730) | E88: =SUMIF('Inventory (Sorted)'!$C$4:$C$730, "Sopdyee", 'Inventory (Sorted)'!$J$4:$J$730) | F88: =E88-D88 | G88: =IF(E88>0, F88/E88, 0)
A89: Chaani | B89: =COUNTIF('Inventory (Sorted)'!$C$4:$C$730, "Chaani") | C89: =SUMIF('Inventory (Sorted)'!$C$4:$C$730, "Chaani", 'Inventory (Sorted)'!$H$4:$H$730) | D89: =SUMIF('Inventory (Sorted)'!$C$4:$C$730, "Chaani", 'Inventory (Sorted)'!$I$4:$I$730) | E89: =SUMIF('Inventory (Sorted)'!$C$4:$C$730, "Chaani", 'Inventory (Sorted)'!$J$4:$J$730) | F89: =E89-D89 | G89: =IF(E89>0, F89/E89, 0)
A90: Crums | B90: =COUNTIF('Inventory (Sorted)'!$C$4:$C$730, "Crums") | C90: =SUMIF('Inventory (Sorted)'!$C$4:$C$730, "Crums", 'Inventory (Sorted)'!$H$4:$H$730) | D90: =SUMIF('Inventory (Sorted)'!$C$4:$C$730, "Crums", 'Inventory (Sorted)'!$I$4:$I$730) | E90: =SUMIF('Inventory (Sorted)'!$C$4:$C$730, "Crums", 'Inventory (Sorted)'!$J$4:$J$730) | F90: =E90-D90 | G90: =IF(E90>0, F90/E90, 0)
A91: Comb | B91: =COUNTIF('Inventory (Sorted)'!$C$4:$C$730, "Comb") | C91: =SUMIF('Inventory (Sorted)'!$C$4:$C$730, "Comb", 'Inventory (Sorted)'!$H$4:$H$730) | D91: =SUMIF('Inventory (Sorted)'!$C$4:$C$730, "Comb", 'Inventory (Sorted)'!$I$4:$I$730) | E91: =SUMIF('Inventory (Sorted)'!$C$4:$C$730, "Comb", 'Inventory (Sorted)'!$J$4:$J$730) | F91: =E91-D91 | G91: =IF(E91>0, F91/E91, 0)
A92: Mayonies | B92: =COUNTIF('Inventory (Sorted)'!$C$4:$C$730, "Mayonies") | C92: =SUMIF('Inventory (Sorted)'!$C$4:$C$730, "Mayonies", 'Inventory (Sorted)'!$H$4:$H$730) | D92: =SUMIF('Inventory (Sorted)'!$C$4:$C$730, "Mayonies", 'Inventory (Sorted)'!$I$4:$I$730) | E92: =SUMIF('Inventory (Sorted)'!$C$4:$C$730, "Mayonies", 'Inventory (Sorted)'!$J$4:$J$730) | F92: =E92-D92 | G92: =IF(E92>0, F92/E92, 0)
A93: Shoe Shine | B93: =COUNTIF('Inventory (Sorted)'!$C$4:$C$730, "Shoe Shine") | C93: =SUMIF('Inventory (Sorted)'!$C$4:$C$730, "Shoe Shine", 'Inventory (Sorted)'!$H$4:$H$730) | D93: =SUMIF('Inventory (Sorted)'!$C$4:$C$730, "Shoe Shine", 'Inventory (Sorted)'!$I$4:$I$730) | E93: =SUMIF('Inventory (Sorted)'!$C$4:$C$730, "Shoe Shine", 'Inventory (Sorted)'!$J$4:$J$730) | F93: =E93-D93 | G93: =IF(E93>0, F93/E93, 0)
A94: Ice Cream Syrup | B94: =COUNTIF('Inventory (Sorted)'!$C$4:$C$730, "Ice Cream Syrup") | C94: =SUMIF('Inventory (Sorted)'!$C$4:$C$730, "Ice Cream Syrup", 'Inventory (Sorted)'!$H$4:$H$730) | D94: =SUMIF('Inventory (Sorted)'!$C$4:$C$730, "Ice Cream Syrup", 'Inventory (Sorted)'!$I$4:$I$730) | E94: =SUMIF('Inventory (Sorted)'!$C$4:$C$730, "Ice Cream Syrup", 'Inventory (Sorted)'!$J$4:$J$730) | F94: =E94-D94 | G94: =IF(E94>0, F94/E94, 0)
A95: Body Powdered | B95: =COUNTIF('Inventory (Sorted)'!$C$4:$C$730, "Body Powdered") | C95: =SUMIF('Inventory (Sorted)'!$C$4:$C$730, "Body Powdered", 'Inventory (Sorted)'!$H$4:$H$730) | D95: =SUMIF('Inventory (Sorted)'!$C$4:$C$730, "Body Powdered", 'Inventory (Sorted)'!$I$4:$I$730) | E95: =SUMIF('Inventory (Sorted)'!$C$4:$C$730, "Body Powdered", 'Inventory (Sorted)'!$J$4:$J$730) | F95: =E95-D95 | G95: =IF(E95>0, F95/E95, 0)
A96: Nail Cutter | B96: =COUNTIF('Inventory (Sorted)'!$C$4:$C$730, "Nail Cutter") | C96: =SUMIF('Inventory (Sorted)'!$C$4:$C$730, "Nail Cutter", 'Inventory (Sorted)'!$H$4:$H$730) | D96: =SUMIF('Inventory (Sorted)'!$C$4:$C$730, "Nail Cutter", 'Inventory (Sorted)'!$I$4:$I$730) | E96: =SUMIF('Inventory (Sorted)'!$C$4:$C$730, "Nail Cutter", 'Inventory (Sorted)'!$J$4:$J$730) | F96: =E96-D96 | G96: =IF(E96>0, F96/E96, 0)
A97: Macaroni | B97: =COUNTIF('Inventory (Sorted)'!$C$4:$C$730, "Macaroni") | C97: =SUMIF('Inventory (Sorted)'!$C$4:$C$730, "Macaroni", 'Inventory (Sorted)'!$H$4:$H$730) | D97: =SUMIF('Inventory (Sorted)'!$C$4:$C$730, "Macaroni", 'Inventory (Sorted)'!$I$4:$I$730) | E97: =SUMIF('Inventory (Sorted)'!$C$4:$C$730, "Macaroni", 'Inventory (Sorted)'!$J$4:$J$730) | F97: =E97-D97 | G97: =IF(E97>0, F97/E97, 0)
A98: Tri Pack | B98: =COUNTIF('Inventory (Sorted)'!$C$4:$C$730, "Tri Pack") | C98: =SUMIF('Inventory (Sorted)'!$C$4:$C$730, "Tri Pack", 'Inventory (Sorted)'!$H$4:$H$730) | D98: =SUMIF('Inventory (Sorted)'!$C$4:$C$730, "Tri Pack", 'Inventory (Sorted)'!$I$4:$I$730) | E98: =SUMIF('Inventory (Sorted)'!$C$4:$C$730, "Tri Pack", 'Inventory (Sorted)'!$J$4:$J$730) | F98: =E98-D98 | G98: =IF(E98>0, F98/E98, 0)
A99: Toilet Jel | B99: =COUNTIF('Inventory (Sorted)'!$C$4:$C$730, "Toilet Jel") | C99: =SUMIF('Inventory (Sorted)'!$C$4:$C$730, "Toilet Jel", 'Inventory (Sorted)'!$H$4:$H$730) | D99: =SUMIF('Inventory (Sorted)'!$C$4:$C$730, "Toilet Jel", 'Inventory (Sorted)'!$I$4:$I$730) | E99: =SUMIF('Inventory (Sorted)'!$C$4:$C$730, "Toilet Jel", 'Inventory (Sorted)'!$J$4:$J$730) | F99: =E99-D99 | G99: =IF(E99>0, F99/E99, 0)
A100: Case | B100: =COUNTIF('Inventory (Sorted)'!$C$4:$C$730, "Case") | C100: =SUMIF('Inventory (Sorted)'!$C$4:$C$730, "Case", 'Inventory (Sorted)'!$H$4:$H$730) | D100: =SUMIF('Inventory (Sorted)'!$C$4:$C$730, "Case", 'Inventory (Sorted)'!$I$4:$I$730) | E100: =SUMIF('Inventory (Sorted)'!$C$4:$C$730, "Case", 'Inventory (Sorted)'!$J$4:$J$730) | F100: =E100-D100 | G100: =IF(E100>0, F100/E100, 0)
A101: Pencil | B101: =COUNTIF('Inventory (Sorted)'!$C$4:$C$730, "Pencil") | C101: =SUMIF('Inventory (Sorted)'!$C$4:$C$730, "Pencil", 'Inventory (Sorted)'!$H$4:$H$730) | D101: =SUMIF('Inventory (Sorted)'!$C$4:$C$730, "Pencil", 'Inventory (Sorted)'!$I$4:$I$730) | E101: =SUMIF('Inventory (Sorted)'!$C$4:$C$730, "Pencil", 'Inventory (Sorted)'!$J$4:$J$730) | F101: =E101-D101 | G101: =IF(E101>0, F101/E101, 0)
A102: Polish | B102: =COUNTIF('Inventory (Sorted)'!$C$4:$C$730, "Polish") | C102: =SUMIF('Inventory (Sorted)'!$C$4:$C$730, "Polish", 'Inventory (Sorted)'!$H$4:$H$730) | D102: =SUMIF('Inventory (Sorted)'!$C$4:$C$730, "Polish", 'Inventory (Sorted)'!$I$4:$I$730) | E102: =SUMIF('Inventory (Sorted)'!$C$4:$C$730, "Polish", 'Inventory (Sorted)'!$J$4:$J$730) | F102: =E102-D102 | G102: =IF(E102>0, F102/E102, 0)
A103: Ketchup | B103: =COUNTIF('Inventory (Sorted)'!$C$4:$C$730, "Ketchup") | C103: =SUMIF('Inventory (Sorted)'!$C$4:$C$730, "Ketchup", 'Inventory (Sorted)'!$H$4:$H$730) | D103: =SUMIF('Inventory (Sorted)'!$C$4:$C$730, "Ketchup", 'Inventory (Sorted)'!$I$4:$I$730) | E103: =SUMIF('Inventory (Sorted)'!$C$4:$C$730, "Ketchup", 'Inventory (Sorted)'!$J$4:$J$730) | F103: =E103-D103 | G103: =IF(E103>0, F103/E103, 0)
...

Sheet Inventory (Sorted)
A1: COMPLETE STORE INVENTORY (SORTED BY CATEGORY)
A3: Barcode / SKU | B3: Product Name | C3: Category Group | D3: Original Category | E3: Purchase Price | F3: Sale Price | G3: Unit Margin | H3: Stock Qty | I3: Total Cost Value | J3: Total Retail Value | K3: Stock Status | L3: Date Added
A4: 1425738481454 | B4: BLACK TIGER ACID | C4: Acid | D4: Acid | E4: 47 | F4: 80 | G4: =F4-E4 | H4: 10 | I4: =E4*H4 | J4: =F4*H4 | K4: =IF(H4<=0, "Out of Stock", IF(H4<=5, "Low Stock", "In Stock")) | L4: 2025-07-14 06:15 PM
A5: 8964003538491 | B5: CORAL AIR FRESHNER BERRY | C5: Air Freshner | D5: Air Freshner | E5: 210 | F5: 350 | G5: =F5-E5 | H5: 3 | I5: =E5*H5 | J5: =F5*H5 | K5: =IF(H5<=0, "Out of Stock", IF(H5<=5, "Low Stock", "In Stock")) | L5: 2025-07-15 12:05 PM
A6: 8964003538675 | B6: CORAL AIR FRESHNER BLACK ICE | C6: Air Freshner | D6: Air Freshner | E6: 210 | F6: 350 | G6: =F6-E6 | H6: 2 | I6: =E6*H6 | J6: =F6*H6 | K6: =IF(H6<=0, "Out of Stock", IF(H6<=5, "Low Stock", "In Stock")) | L6: 2025-07-15 12:01 PM
A7: 8964003538453 | B7: CORAL AIR FRESHNER OCEAN | C7: Air Freshner | D7: Air Freshner | E7: 210 | F7: 350 | G7: =F7-E7 | H7: 12 | I7: =E7*H7 | J7: =F7*H7 | K7: =IF(H7<=0, "Out of Stock", IF(H7<=5, "Low Stock", "In Stock")) | L7: 2025-07-15 12:02 PM
A8: 8964003538507 | B8: CORAL AIR FRESHNER ORANGE | C8: Air Freshner | D8: Air Freshner | E8: 210 | F8: 350 | G8: =F8-E8 | H8: 4 | I8: =E8*H8 | J8: =F8*H8 | K8: =IF(H8<=0, "Out of Stock", IF(H8<=5, "Low Stock", "In Stock")) | L8: 2025-07-15 12:03 PM
A9: 8964003538477 | B9: CORAL AIR FRESHNER | C9: Air Fresshner | D9: Air Fresshner | E9: 210 | F9: 350 | G9: =F9-E9 | H9: 3 | I9: =E9*H9 | J9: =F9*H9 | K9: =IF(H9<=0, "Out of Stock", IF(H9<=5, "Low Stock", "In Stock")) | L9: 2025-07-15 12:00 PM
A10: 8991111109121 | B10: JOHANSONS BABY POWDER | C10: Baby Care | D10: Baby Powder | E10: 155 | F10: 200 | G10: =F10-E10 | H10: 11 | I10: =E10*H10 | J10: =F10*H10 | K10: =IF(H10<=0, "Out of Stock", IF(H10<=5, "Low Stock", "In Stock")) | L10: 2025-07-14 03:46 PM
A11: 8063304010009 | B11: COOL SOFT BABY WIPES | C11: Baby Care | D11: Baby Wipes | E11: 380 | F11: 450 | G11: =F11-E11 | H11: 13 | I11: =E11*H11 | J11: =F11*H11 | K11: =IF(H11<=0, "Out of Stock", IF(H11<=5, "Low Stock", "In Stock")) | L11: 2025-07-13 03:45 PM
A12: 8993560027544 | B12: DETTOL BABY WIPES | C12: Baby Care | D12: Baby Wipes | E12: 150 | F12: 250 | G12: =F12-E12 | H12: 8 | I12: =E12*H12 | J12: =F12*H12 | K12: =IF(H12<=0, "Out of Stock", IF(H12<=5, "Low Stock", "In Stock")) | L12: 2025-07-13 03:52 PM
A13: 5559666888873 | B13: JEEP BABY WIPES | C13: Baby Care | D13: Baby Wipes | E13: 150 | F13: 250 | G13: =F13-E13 | H13: 7 | I13: =E13*H13 | J13: =F13*H13 | K13: =IF(H13<=0, "Out of Stock", IF(H13<=5, "Low Stock", "In Stock")) | L13: 2025-07-13 03:47 PM
A14: 257896548349 | B14: RAHAT BABY WIPES | C14: Baby Care | D14: Baby Wipes | E14: 100 | F14: 150 | G14: =F14-E14 | H14: 23 | I14: =E14*H14 | J14: =F14*H14 | K14: =IF(H14<=0, "Out of Stock", IF(H14<=5, "Low Stock", "In Stock")) | L14: 2025-07-13 03:37 PM
A15: 5126511533457 | B15: ROCKET BABY WIPES | C15: Baby Care | D15: Baby Wipes | E15: 108 | F15: 160 | G15: =F15-E15 | H15: 25 | I15: =E15*H15 | J15: =F15*H15 | K15: =IF(H15<=0, "Out of Stock", IF(H15<=5, "Low Stock", "In Stock")) | L15: 2025-07-13 03:37 PM
... A730: 6936965445683 | B730: CORRECTION PEN WHITENER | C730: Whitener | D730: Whitener | E730: 70 | F730: 100 | G730: =F730-E730 | H730: 18 | I730: =E730*H730 | J730: =F730*H730 | K730: =IF(H730<=0, "Out of Stock", IF(H730<=5, "Low Stock", "In Stock")) | L730: 2025-07-13 06:42 PM
B731: TOTALS | H731: =SUM(H4:H730) | I731: =SUM(I4:I730) | J731: =SUM(J4:J730)
